dnit_updater.py
dnit_updater-0.1.1.dist-info/METADATA
dnit_updater-0.1.1.dist-info/WHEEL
dnit_updater-0.1.1.dist-info/RECORD
